inferno/__init__.py
inferno/__main__.py
inferno/version.py
inferno/api/__init__.py
inferno/api/routes.py
inferno/api/server.py
inferno/cli/__init__.py
inferno/cli/commands.py
inferno/client/__init__.py
inferno/client/client.py
inferno/client/config.py
inferno/client/exceptions.py
inferno/client/models.py
inferno/client/utils.py
inferno/core/__init__.py
inferno/core/gguf_reader.py
inferno/core/llm.py
inferno/core/model_manager.py
inferno/core/quantizer.py
inferno/core/ram_estimator.py
inferno/utils/__init__.py
inferno/utils/config.py
inferno/utils/helpers.py
inferno_llm-0.1.7.dist-info/licenses/LICENSE
inferno_llm-0.1.7.dist-info/METADATA
inferno_llm-0.1.7.dist-info/WHEEL
inferno_llm-0.1.7.dist-info/entry_points.txt
inferno_llm-0.1.7.dist-info/top_level.txt
inferno_llm-0.1.7.dist-info/RECORD
